pysvgchart/__init__.py
pysvgchart/axes.py
pysvgchart/charts.py
pysvgchart/helpers.py
pysvgchart/legends.py
pysvgchart/scales.py
pysvgchart/series.py
pysvgchart/shapes.py
pysvgchart/shared.py
pysvgchart/styles.py
pysvgchart-0.6.2.dist-info/licenses/LICENSE
pysvgchart-0.6.2.dist-info/METADATA
pysvgchart-0.6.2.dist-info/WHEEL
pysvgchart-0.6.2.dist-info/top_level.txt
pysvgchart-0.6.2.dist-info/RECORD
